satquest/__init__.py
satquest/cnf.py
satquest/constants.py
satquest/problem.py
satquest/question.py
satquest/satquest_utils.py
satquest-0.2.0.dist-info/METADATA
satquest-0.2.0.dist-info/WHEEL
satquest-0.2.0.dist-info/licenses/LICENSE
satquest-0.2.0.dist-info/RECORD
