Metadata-Version: 2.4
Name: SATQuest
Version: 0.2.0
Summary: A Verifier for Logical Reasoning Evaluation and Reinforcement Fine-Tuning of LLMs
Project-URL: Homepage, https://github.com/sdpkjc/satquest
Project-URL: Documentation, https://github.com/sdpkjc/satquest#readme
Project-URL: Source, https://github.com/sdpkjc/satquest
Project-URL: Issues, https://github.com/sdpkjc/satquest/issues
Author-email: Yanxiao Zhao <pazyx728@gmail.com>
Maintainer-email: Yanxiao Zhao <pazyx728@gmail.com>
License: MIT License
License-File: LICENSE
Keywords: LLM,evaluation,reasoning,reinforcement-learning
Classifier: Development Status :: 4 - Beta
Classifier: Intended Audience :: Developers
Classifier: Intended Audience :: Science/Research
Classifier: License :: OSI Approved :: MIT License
Classifier: Programming Language :: Python :: 3
Classifier: Programming Language :: Python :: 3 :: Only
Classifier: Programming Language :: Python :: 3.9
Classifier: Programming Language :: Python :: 3.10
Classifier: Programming Language :: Python :: 3.11
Classifier: Programming Language :: Python :: 3.12
Classifier: Programming Language :: Python :: 3.13
Classifier: Topic :: Scientific/Engineering :: Artificial Intelligence
Requires-Python: >=3.10
Requires-Dist: python-sat==1.8.dev14
